{"rolling_win": 1, "cat_hour": true, "cat_month": true, "with_interact": false, "split_direct": false, "fill_missing": true, "group_hour": 2, "split_lists": [[0.55, 0.2, 0.25], [0.55, 0.2, 0.25], [0.75, 0.25]], "fire_dict": {"w_speed": 2.0, "shift": 72, "roll": 216, "damp_surface": 1.9, "wind_damp": 1, "wind_lag": 1, "split_direct": 0}, "lag_dict": {"n_max": 15, "step": 10, "roll": true}, "use_impute": 0, "x_cols_org": ["Temperature(C)", "Wind_Speed(kmph)", "wind_CALM", "wind_N", "wind_S", "wind_W", "is_rain", "is_holiday", "is_weekend", "time_of_day_[2, 4)", "time_of_day_[4, 6)", "time_of_day_[8, 10)", "time_of_day_[10, 12)", "time_of_day_[12, 14)", "time_of_day_[14, 16)", "time_of_day_[16, 18)", "time_of_day_[18, 20)", "time_of_day_[20, 22)", "time_of_day_[22, 24)", "month_1", "month_2", "month_3", "month_4", "month_5", "month_6", "month_7", "month_8", "month_10", "fire_0_100", "fire_100_200", "fire_200_400", "fire_400_800", "fire_800_900"], "x_cols": ["Temperature(C)", "Wind_Speed(kmph)", "wind_CALM", "wind_N", "wind_S", "wind_W", "is_rain", "is_holiday", "is_weekend", "time_of_day_[2, 4)", "time_of_day_[4, 6)", "time_of_day_[8, 10)", "time_of_day_[10, 12)", "time_of_day_[12, 14)", "time_of_day_[14, 16)", "time_of_day_[16, 18)", "time_of_day_[18, 20)", "time_of_day_[20, 22)", "time_of_day_[22, 24)", "month_1", "month_2", "month_3", "month_4", "month_5", "month_6", "month_7", "month_8", "month_10", "fire_0_100", "fire_100_200", "fire_200_400", "fire_400_800", "fire_800_900"], "zone_list": [0, 100, 200, 400, 800, 900], "fire_cols": ["fire_0_100", "fire_100_200", "fire_200_400", "fire_400_800", "fire_800_900"], "rf_score": {"val_r2_score": 0.4625, "val_r2": 0.6429, "val_mean_squared_error": 72.0376, "val_mean_absolute_error": 6.6431, "val_mean_absolute_percentage_error": 41.1391, "val_median_absolute_error": 5.0561}, "rf_params": {"bootstrap": true, "ccp_alpha": 0.0, "criterion": "mse", "max_depth": null, "max_features": "sqrt", "max_leaf_nodes": null, "max_samples": null, "min_impurity_decrease": 0.0, "min_impurity_split": null, "min_samples_leaf": 1, "min_samples_split": 20, "min_weight_fraction_leaf": 0.0, "n_estimators": 220, "n_jobs": -2, "oob_score": false, "random_state": 42, "verbose": 0, "warm_start": false}, "rf_avg_score": {"avg_test_r2_score": 0.6634, "avg_test_r2": 0.8745, "avg_test_mean_squared_error": 48.69, "avg_test_mean_absolute_error": 5.5571, "avg_test_mean_absolute_percentage_error": 41.2794, "avg_test_median_absolute_error": 4.7703}, "rolling": 1}